{
  "isPromise": true,
  "volume": "sc.suttaplex",
  "args": [
    "https://suttacentral.net/api/suttaplex/mn131"
  ],
  "value": [
    {
      "acronym": "MN 131",
      "alt_volpages": null,
      "biblio": null,
      "blurb": "This discourse opens with a short but powerful set of verses extolling the benefits of insight into the here and now, followed by an explanation.",
      "difficulty": {
        "level": 2,
        "name": "intermediate"
      },
      "original_title": "Bhaddekarattasutta",
      "parallel_count": 15,
      "root_lang": "pli",
      "root_lang_name": "Pāli",
      "translated_title": "One Fine Night ",
      "translations": [
        {
          "author": "Mahāsaṅgīti Tipiṭaka Buddhavasse 2500",
          "author_short": "ms",
          "author_uid": "ms",
          "id": "mn131_root-pli-ms",
          "is_root": true,
          "lang": "pli",
          "lang_name": "Pāli",
          "publication_date": null,
          "segmented": true,
          "title": null,
          "volpage": null
        },
        {
          "author": "বিনয়েন্দ্রনাথ চৌধুরী",
          "author_short": "চৌধুরী",
          "author_uid": "chowdhury",
          "id": "bn_mn131_chowdhury",
          "is_root": false,
          "lang": "bn",
          "lang_name": "Bengali",
          "publication_date": null,
          "segmented": false,
          "volpage": null
        },
        {
          "author": "Jambudipa",
          "author_short": "Jambudipa",
          "author_uid": "jambudipa",
          "id": "ca_mn131_jambudipa",
          "is_root": false,
          "lang": "ca",
          "lang_name": "Català",
          "publication_date": "2012",
          "segmented": false,
          "volpage": null
        },
        {
          "author": "Mettiko Bhikkhu",
          "author_short": "Mettiko",
          "author_uid": "mettiko",
          "id": "de_mn131_mettiko",
          "is_root": false,
          "lang": "de",
          "lang_name": "Deutsch",
          "publication_date": "2001",
          "segmented": false,
          "volpage": null
        },
        {
          "author": "Bhikkhu Sujato",
          "author_short": "sujato",
          "author_uid": "sujato",
          "id": "mn131_translation-en-sujato",
          "is_root": false,
          "lang": "en",
          "lang_name": "English",
          "publication_date": null,
          "segmented": true,
          "title": "One Fine Night ",
          "volpage": null
        },
        {
          "author": "Anton P. Baron",
          "author_short": "Baron",
          "author_uid": "baron",
          "id": "es_mn131_baron",
          "is_root": false,
          "lang": "es",
          "lang_name": "Español",
          "publication_date": null,
          "segmented": false,
          "volpage": null
        },
        {
          "author": "Rahul Sankrityayan",
          "author_short": "Sankrityayan",
          "author_uid": "sankrityayan",
          "id": "hi_mn131_sankrityayan",
          "is_root": false,
          "lang": "hi",
          "lang_name": "हिन्दी",
          "publication_date": null,
          "segmented": false,
          "volpage": null
        },
        {
          "author": "Nyitrai Gábor",
          "author_short": "Nyitrai",
          "author_uid": "nyitrai",
          "id": "hu_mn131_nyitrai",
          "is_root": false,
          "lang": "hu",
          "lang_name": "Magyar",
          "publication_date": "2008",
          "segmented": false,
          "volpage": null
        },
        {
          "author": "Indra Anggara",
          "author_short": "Anggara",
          "author_uid": "anggara",
          "id": "id_mn131_anggara",
          "is_root": false,
          "lang": "id",
          "lang_name": "Indonesian",
          "publication_date": null,
          "segmented": false,
          "volpage": null
        },
        {
          "author": "De Lorenzo, Pier Antonio Morniroli, Enrico Federici",
          "author_short": "Lorenzo …",
          "author_uid": "lorenzo-morniroli-federici",
          "id": "it_mn131_lorenzo-morniroli-federici",
          "is_root": false,
          "lang": "it",
          "lang_name": "Italiano",
          "publication_date": "2007",
          "segmented": false,
          "volpage": null
        },
        {
          "author": "Pitaka Myanmar Translation",
          "author_short": "PMT",
          "author_uid": "pmt",
          "id": "my_mn131_pmt",
          "is_root": false,
          "lang": "my",
          "lang_name": "မြန်မာဘာသာ",
          "publication_date": null,
          "segmented": false,
          "volpage": null
        },
        {
          "author": "Guy Eugène Dubois",
          "author_short": "Dubois",
          "author_uid": "dubois",
          "id": "nl_mn131_dubois",
          "is_root": false,
          "lang": "nl",
          "lang_name": "Nederlands",
          "publication_date": null,
          "segmented": false,
          "volpage": null
        },
        {
          "author": "Kåre A. Lie",
          "author_short": "Lie",
          "author_uid": "lie",
          "id": "no_mn131_lie",
          "is_root": false,
          "lang": "no",
          "lang_name": "Norsk",
          "publication_date": "2013",
          "segmented": false,
          "volpage": null
        },
        {
          "author": "Michael Beisert",
          "author_short": "Beisert",
          "author_uid": "beisert",
          "id": "pt_mn131_beisert",
          "is_root": false,
          "lang": "pt",
          "lang_name": "Português",
          "publication_date": "2014",
          "segmented": false,
          "volpage": null
        },
        {
          "author": "баян купи-ка",
          "author_short": "купи-ка",
          "author_uid": "kupi-ka",
          "id": "ru_mn131_kupi-ka",
          "is_root": false,
          "lang": "ru",
          "lang_name": "ру́сский язы́к",
          "publication_date": null,
          "segmented": false,
          "volpage": null
        },
        {
          "author": "SV",
          "author_short": "SV",
          "author_uid": "sv",
          "id": "ru_mn131_sv",
          "is_root": false,
          "lang": "ru",
          "lang_name": "ру́сский язы́к",
          "publication_date": "2016",
          "segmented": false,
          "volpage": null
        },
        {
          "author": "A.P. de Zoysa",
          "author_short": "Zoysa",
          "author_uid": "zoysa",
          "id": "si_mn131_zoysa",
          "is_root": false,
          "lang": "si",
          "lang_name": "සිංහල",
          "publication_date": null,
          "segmented": false,
          "volpage": null
        },
        {
          "author": "Branislav Kovačević",
          "author_short": "Kovačević",
          "author_uid": "kovacevic",
          "id": "sr_mn131_kovacevic",
          "is_root": false,
          "lang": "sr",
          "lang_name": "Srpski",
          "publication_date": "2014",
          "segmented": false,
          "volpage": null
        },
        {
          "author": "Kerstin Jönhagen",
          "author_short": "Jönhagen",
          "author_uid": "jonhagen",
          "id": "sv_mn131_jonhagen",
          "is_root": false,
          "lang": "sv",
          "lang_name": "Svenska",
          "publication_date": null,
          "segmented": false,
          "volpage": null
        },
        {
          "author": "Ben Arasu",
          "author_short": "Arasu",
          "author_uid": "arasu",
          "id": "ta_mn131_arasu",
          "is_root": false,
          "lang": "ta",
          "lang_name": "தமிழ்",
          "publication_date": null,
          "segmented": false,
          "volpage": null
        },
        {
          "author": "Siam Rath",
          "author_short": "Siam Rath",
          "author_uid": "siam_rath",
          "id": "th_mn131_siam_rath",
          "is_root": false,
          "lang": "th",
          "lang_name": "ไทย",
          "publication_date": null,
          "segmented": false,
          "volpage": null
        },
        {
          "author": "Thích Minh Châu",
          "author_short": "Minh Châu",
          "author_uid": "minh_chau",
          "id": "vi_mn131_minh_chau",
          "is_root": false,
          "lang": "vi",
          "lang_name": "Tiếng Việt",
          "publication_date": null,
          "segmented": false,
          "volpage": null
        },
        {
          "author": "莊春江",
          "author_short": "莊春江",
          "author_uid": "zhuang",
          "id": "zh_mn131_zhuang",
          "is_root": false,
          "lang": "zh",
          "lang_name": "汉语",
          "publication_date": null,
          "segmented": false,
          "volpage": null
        }
      ],
      "type": "leaf",
      "uid": "mn131",
      "volpages": " PTS 3.188, PTS 3.189"
    }
  ]
}